[
  {
    "1": "-",
    "2": "-",
    "3": "-",
    "4": "-",
    "5": "-",
    "6": "-",
    "7": "-",
    "8": "-",
    "9": "-",
    "10": "-",
    "11": "-",
    "12": "-",
    "13": "-",
    "14": "-",
    "15": "-",
    "16": "-",
    "17": "-",
    "18": "-",
    "19": "-",
    "class": 4,
    "test": 2,
    "category": 2,
    "no": 1,
    "completed": 0,
    "name": "ANA CAROLINE DA SILVA RAMUALDO"
  },
  {
    "1": "-",
    "2": "-",
    "3": "-",
    "4": "-",
    "5": "-",
    "6": "-",
    "7": "-",
    "8": "-",
    "9": "-",
    "10": "-",
    "11": "-",
    "12": "-",
    "13": "-",
    "14": "-",
    "15": "-",
    "16": "-",
    "17": "-",
    "18": "-",
    "19": "-",
    "class": 4,
    "test": 2,
    "category": 2,
    "no": 2,
    "completed": 0,
    "name": "ANA CLARA FRANÇA DE OLIVEIRA SILVA"
  },
  {
    "1": "C",
    "2": "C",
    "3": "A",
    "4": "B",
    "5": "A",
    "6": "C",
    "7": "A",
    "8": "B",
    "9": "D",
    "10": "B",
    "11": "A",
    "12": "B",
    "13": "A",
    "14": "D",
    "15": "A",
    "16": "A",
    "17": "A",
    "18": "A",
    "19": "C",
    "class": 4,
    "test": 2,
    "category": 2,
    "no": 3,
    "completed": 1,
    "name": "ANA LUIZA BARBOSA ZAULI"
  },
  {
    "1": "C",
    "2": "D",
    "3": "C",
    "4": "C",
    "5": "C",
    "6": "C",
    "7": "B",
    "8": "D",
    "9": "B",
    "10": "B",
    "11": "D",
    "12": "A",
    "13": "C",
    "14": "A",
    "15": "B",
    "16": "A",
    "17": "B",
    "18": "A",
    "19": "B",
    "class": 4,
    "test": 2,
    "category": 2,
    "no": 4,
    "completed": 1,
    "name": "ARTHUR BRANDAO STOCCO"
  },
  {
    "1": "D",
    "2": "A",
    "3": "B",
    "4": "D",
    "5": "A",
    "6": "B",
    "7": "A",
    "8": "C",
    "9": "D",
    "10": "B",
    "11": "A",
    "12": "C",
    "13": "C",
    "14": "C",
    "15": "C",
    "16": "A",
    "17": "A",
    "18": "A",
    "19": "C",
    "class": 4,
    "test": 2,
    "category": 2,
    "no": 5,
    "completed": 1,
    "name": "BEATRIZ YARA DA SILVA RUSSI"
  },
  {
    "1": "C",
    "2": "A",
    "3": "C",
    "4": "D",
    "5": "A",
    "6": "B",
    "7": "D",
    "8": "B",
    "9": "C",
    "10": "B",
    "11": "B",
    "12": "D",
    "13": "C",
    "14": "D",
    "15": "B",
    "16": "D",
    "17": "A",
    "18": "B",
    "19": "C",
    "class": 4,
    "test": 2,
    "category": 2,
    "no": 6,
    "completed": 1,
    "name": "CRISTIAN CABRAL TUON"
  },
  {
    "1": "C",
    "2": "D",
    "3": "D",
    "4": "C",
    "5": "B",
    "6": "B",
    "7": "A",
    "8": "C",
    "9": "C",
    "10": "B",
    "11": "D",
    "12": "A",
    "13": "A",
    "14": "A",
    "15": "A",
    "16": "B",
    "17": "C",
    "18": "B",
    "19": "D",
    "class": 4,
    "test": 2,
    "category": 2,
    "no": 7,
    "completed": 1,
    "name": "DANIELA SUELLEN DO CARMO SILVA"
  },
  {
    "1": "D",
    "2": "A",
    "3": "B",
    "4": "B",
    "5": "A",
    "6": "D",
    "7": "C",
    "8": "D",
    "9": "A",
    "10": "A",
    "11": "C",
    "12": "C",
    "13": "B",
    "14": "D",
    "15": "C",
    "16": "A",
    "17": "B",
    "18": "B",
    "19": "D",
    "class": 4,
    "test": 2,
    "category": 2,
    "no": 8,
    "completed": 1,
    "name": "ENZO MARROFFINO"
  },
  {
    "1": "D",
    "2": "C",
    "3": "B",
    "4": "A",
    "5": "B",
    "6": "C",
    "7": "D",
    "8": "B",
    "9": "A",
    "10": "D",
    "11": "C",
    "12": "B",
    "13": "A",
    "14": "C",
    "15": "D",
    "16": "D",
    "17": "A",
    "18": "B",
    "19": "C",
    "class": 4,
    "test": 2,
    "category": 2,
    "no": 9,
    "completed": 1,
    "name": "FELIPE FERREIRA DE SOUZA"
  },
  {
    "1": "C",
    "2": "C",
    "3": "B",
    "4": "D",
    "5": "A",
    "6": "C",
    "7": "A",
    "8": "B",
    "9": "B",
    "10": "B",
    "11": "D",
    "12": "B",
    "13": "C",
    "14": "A",
    "15": "B",
    "16": "C",
    "17": "C",
    "18": "B",
    "19": "B",
    "class": 4,
    "test": 2,
    "category": 2,
    "no": 10,
    "completed": 1,
    "name": "GABRIEL AMORIM MIETTI"
  },
  {
    "1": "C",
    "2": "B",
    "3": "C",
    "4": "A",
    "5": "A",
    "6": "B",
    "7": "D",
    "8": "D",
    "9": "B",
    "10": "B",
    "11": "D",
    "12": "C",
    "13": "C",
    "14": "D",
    "15": "A",
    "16": "D",
    "17": "D",
    "18": "A",
    "19": "B",
    "class": 4,
    "test": 2,
    "category": 2,
    "no": 11,
    "completed": 1,
    "name": "GUSTAVO DA SILVA CASSEMIRO"
  },
  {
    "1": "B",
    "2": "A",
    "3": "C",
    "4": "C",
    "5": "B",
    "6": "B",
    "7": "A",
    "8": "B",
    "9": "D",
    "10": "B",
    "11": "C",
    "12": "D",
    "13": "B",
    "14": "A",
    "15": "C",
    "16": "A",
    "17": "C",
    "18": "C",
    "19": "D",
    "class": 4,
    "test": 2,
    "category": 2,
    "no": 12,
    "completed": 1,
    "name": "HENRIQUE AUGUSTO ALVES BASSAN"
  },
  {
    "1": "B",
    "2": "D",
    "3": "D",
    "4": "B",
    "5": "C",
    "6": "C",
    "7": "D",
    "8": "B",
    "9": "B",
    "10": "C",
    "11": "D",
    "12": "C",
    "13": "C",
    "14": "A",
    "15": "B",
    "16": "C",
    "17": "A",
    "18": "D",
    "19": "C",
    "class": 4,
    "test": 2,
    "category": 2,
    "no": 13,
    "completed": 1,
    "name": "HENRY FERREIRA MELO TAVARES"
  },
  {
    "1": "D",
    "2": "D",
    "3": "D",
    "4": "B",
    "5": "A",
    "6": "C",
    "7": "D",
    "8": "B",
    "9": "B",
    "10": "D",
    "11": "D",
    "12": "C",
    "13": "B",
    "14": "D",
    "15": "D",
    "16": "A",
    "17": "A",
    "18": "B",
    "19": "A",
    "class": 4,
    "test": 2,
    "category": 2,
    "no": 14,
    "completed": 1,
    "name": "ISABELA CRISTINA DOS SANTOS"
  },
  {
    "1": "C",
    "2": "B",
    "3": "C",
    "4": "A",
    "5": "A",
    "6": "B",
    "7": "D",
    "8": "D",
    "9": "D",
    "10": "B",
    "11": "D",
    "12": "C",
    "13": "C",
    "14": "A",
    "15": "A",
    "16": "D",
    "17": "B",
    "18": "A",
    "19": "A",
    "class": 4,
    "test": 2,
    "category": 2,
    "no": 15,
    "completed": 1,
    "name": "JEFFERSON DE SENA SILVA JUNIOR"
  },
  {
    "1": "-",
    "2": "-",
    "3": "-",
    "4": "-",
    "5": "-",
    "6": "-",
    "7": "-",
    "8": "-",
    "9": "-",
    "10": "-",
    "11": "-",
    "12": "-",
    "13": "-",
    "14": "-",
    "15": "-",
    "16": "-",
    "17": "-",
    "18": "-",
    "19": "-",
    "class": 4,
    "test": 2,
    "category": 2,
    "no": 16,
    "completed": 0,
    "name": "JOAO PEDRO DA SILVA LIMA"
  },
  {
    "1": "-",
    "2": "-",
    "3": "-",
    "4": "-",
    "5": "-",
    "6": "-",
    "7": "-",
    "8": "-",
    "9": "-",
    "10": "-",
    "11": "-",
    "12": "-",
    "13": "-",
    "14": "-",
    "15": "-",
    "16": "-",
    "17": "-",
    "18": "-",
    "19": "-",
    "class": 4,
    "test": 2,
    "category": 2,
    "no": 17,
    "completed": 0,
    "name": "KAYNÃ JESUS ROSA"
  },
  {
    "1": "B",
    "2": "C",
    "3": "A",
    "4": "A",
    "5": "C",
    "6": "D",
    "7": "B",
    "8": "B",
    "9": "A",
    "10": "B",
    "11": "C",
    "12": "B",
    "13": "D",
    "14": "C",
    "15": "B",
    "16": "C",
    "17": "B",
    "18": "B",
    "19": "C",
    "class": 4,
    "test": 2,
    "category": 2,
    "no": 18,
    "completed": 1,
    "name": "KELVIN GONÇALVES MIGUEL"
  },
  {
    "1": "D",
    "2": "D",
    "3": "B",
    "4": "B",
    "5": "A",
    "6": "C",
    "7": "C",
    "8": "B",
    "9": "C",
    "10": "A",
    "11": "D",
    "12": "B",
    "13": "C",
    "14": "A",
    "15": "A",
    "16": "A",
    "17": "A",
    "18": "A",
    "19": "B",
    "class": 4,
    "test": 2,
    "category": 2,
    "no": 19,
    "completed": 1,
    "name": "LAURA GOUVEIA DA SILVA"
  },
  {
    "1": "C",
    "2": "A",
    "3": "A",
    "4": "B",
    "5": "B",
    "6": "A",
    "7": "D",
    "8": "C",
    "9": "C",
    "10": "B",
    "11": "D",
    "12": "B",
    "13": "B",
    "14": "A",
    "15": "C",
    "16": "B",
    "17": "A",
    "18": "C",
    "19": "A",
    "class": 4,
    "test": 2,
    "category": 2,
    "no": 20,
    "completed": 1,
    "name": "LEANDRA COSTA FARIA"
  },
  {
    "1": "D",
    "2": "D",
    "3": "C",
    "4": "B",
    "5": "A",
    "6": "B",
    "7": "C",
    "8": "C",
    "9": "D",
    "10": "B",
    "11": "D",
    "12": "A",
    "13": "B",
    "14": "C",
    "15": "D",
    "16": "A",
    "17": "A",
    "18": "A",
    "19": "B",
    "class": 4,
    "test": 2,
    "category": 2,
    "no": 21,
    "completed": 1,
    "name": "LEONARDO SILVA SARTORATO"
  },
  {
    "1": "D",
    "2": "A",
    "3": "B",
    "4": "C",
    "5": "A",
    "6": "C",
    "7": "C",
    "8": "B",
    "9": "B",
    "10": "A",
    "11": "A",
    "12": "C",
    "13": "C",
    "14": "D",
    "15": "A",
    "16": "A",
    "17": "D",
    "18": "B",
    "19": "C",
    "class": 4,
    "test": 2,
    "category": 2,
    "no": 22,
    "completed": 1,
    "name": "MARIA CLARA FUMACHE DA SILVEIRA"
  },
  {
    "1": "D",
    "2": "D",
    "3": "B",
    "4": "D",
    "5": "A",
    "6": "C",
    "7": "D",
    "8": "B",
    "9": "B",
    "10": "D",
    "11": "A",
    "12": "A",
    "13": "A",
    "14": "A",
    "15": "D",
    "16": "B",
    "17": "A",
    "18": "A",
    "19": "B",
    "class": 4,
    "test": 2,
    "category": 2,
    "no": 23,
    "completed": 1,
    "name": "MARIA EDUARDA SAMPAIO DE OLIVEIRA"
  },
  {
    "1": "D",
    "2": "C",
    "3": "C",
    "4": "B",
    "5": "A",
    "6": "D",
    "7": "A",
    "8": "C",
    "9": "C",
    "10": "A",
    "11": "B",
    "12": "A",
    "13": "C",
    "14": "A",
    "15": "C",
    "16": "C",
    "17": "A",
    "18": "B",
    "19": "B",
    "class": 4,
    "test": 2,
    "category": 2,
    "no": 24,
    "completed": 1,
    "name": "MARIA GABRIELA AMBROSIN DA SILVA"
  },
  {
    "1": "B",
    "2": "C",
    "3": "D",
    "4": "D",
    "5": "A",
    "6": "B",
    "7": "B",
    "8": "C",
    "9": "D",
    "10": "D",
    "11": "D",
    "12": "B",
    "13": "B",
    "14": "C",
    "15": "B",
    "16": "B",
    "17": "D",
    "18": "A",
    "19": "B",
    "class": 4,
    "test": 2,
    "category": 2,
    "no": 25,
    "completed": 1,
    "name": "MATEUS RYAN SILVEIRA BUOSI"
  },
  {
    "1": "C",
    "2": "D",
    "3": "B",
    "4": "B",
    "5": "A",
    "6": "B",
    "7": "D",
    "8": "C",
    "9": "B",
    "10": "D",
    "11": "D",
    "12": "C",
    "13": "B",
    "14": "A",
    "15": "C",
    "16": "A",
    "17": "A",
    "18": "B",
    "19": "C",
    "class": 4,
    "test": 2,
    "category": 2,
    "no": 26,
    "completed": 1,
    "name": "MURILO CORREDOR"
  },
  {
    "1": "-",
    "2": "-",
    "3": "-",
    "4": "-",
    "5": "-",
    "6": "-",
    "7": "-",
    "8": "-",
    "9": "-",
    "10": "-",
    "11": "-",
    "12": "-",
    "13": "-",
    "14": "-",
    "15": "-",
    "16": "-",
    "17": "-",
    "18": "-",
    "19": "-",
    "class": 4,
    "test": 2,
    "category": 2,
    "no": 27,
    "completed": 0,
    "name": "NATALIA RIBEIRO ROSA"
  },
  {
    "1": "D",
    "2": "D",
    "3": "B",
    "4": "B",
    "5": "B",
    "6": "B",
    "7": "B",
    "8": "C",
    "9": "D",
    "10": "B",
    "11": "B",
    "12": "B",
    "13": "C",
    "14": "C",
    "15": "B",
    "16": "A",
    "17": "D",
    "18": "A",
    "19": "D",
    "class": 4,
    "test": 2,
    "category": 2,
    "no": 28,
    "completed": 1,
    "name": "PEDRO HENRIQUE CARRARO"
  },
  {
    "1": "-",
    "2": "-",
    "3": "-",
    "4": "-",
    "5": "-",
    "6": "-",
    "7": "-",
    "8": "-",
    "9": "-",
    "10": "-",
    "11": "-",
    "12": "-",
    "13": "-",
    "14": "-",
    "15": "-",
    "16": "-",
    "17": "-",
    "18": "-",
    "19": "-",
    "class": 4,
    "test": 2,
    "category": 2,
    "no": 29,
    "completed": 0,
    "name": "RIQUELME DE OLIVEIRA MAXIMO"
  },
  {
    "1": "D",
    "2": "A",
    "3": "C",
    "4": "B",
    "5": "D",
    "6": "B",
    "7": "C",
    "8": "B",
    "9": "C",
    "10": "A",
    "11": "D",
    "12": "B",
    "13": "A",
    "14": "D",
    "15": "B",
    "16": "A",
    "17": "D",
    "18": "A",
    "19": "B",
    "class": 4,
    "test": 2,
    "category": 2,
    "no": 30,
    "completed": 1,
    "name": "RYAN TEODORO DE FRANÇA"
  },
  {
    "1": "C",
    "2": "C",
    "3": "B",
    "4": "B",
    "5": "A",
    "6": "A",
    "7": "A",
    "8": "D",
    "9": "D",
    "10": "A",
    "11": "D",
    "12": "B",
    "13": "B",
    "14": "A",
    "15": "B",
    "16": "A",
    "17": "C",
    "18": "A",
    "19": "D",
    "class": 4,
    "test": 2,
    "category": 2,
    "no": 31,
    "completed": 1,
    "name": "STÉFANY KAROLINE MARTINS ALVES"
  },
  {
    "1": "A",
    "2": "A",
    "3": "C",
    "4": "D",
    "5": "B",
    "6": "B",
    "7": "B",
    "8": "B",
    "9": "D",
    "10": "B",
    "11": "B",
    "12": "C",
    "13": "C",
    "14": "A",
    "15": "B",
    "16": "B",
    "17": "C",
    "18": "C",
    "19": "A",
    "class": 4,
    "test": 2,
    "category": 2,
    "no": 32,
    "completed": 1,
    "name": "VINÍCIUS CAETANO PEREIRA"
  },
  {
    "1": "C",
    "2": "C",
    "3": "C",
    "4": "C",
    "5": "B",
    "6": "A",
    "7": "C",
    "8": "B",
    "9": "A",
    "10": "B",
    "11": "D",
    "12": "D",
    "13": "C",
    "14": "C",
    "15": "B",
    "16": "A",
    "17": "A",
    "18": "A",
    "19": "C",
    "class": 4,
    "test": 2,
    "category": 2,
    "no": 33,
    "completed": 1,
    "name": "MATEUS LIAM DE OLIVEIRA  FARIA"
  }
]